LICENSE
README.md
setup.cfg
setup.py
qt_colored_logger/__init__.py
qt_colored_logger.egg-info/PKG-INFO
qt_colored_logger.egg-info/SOURCES.txt
qt_colored_logger.egg-info/dependency_links.txt
qt_colored_logger.egg-info/top_level.txt
qt_colored_logger/basic/__init__.py
qt_colored_logger/basic/basic_logger.py
qt_colored_logger/basic/exceptions.py
qt_colored_logger/basic/patterns.py
qt_colored_logger/logger/__init__.py
qt_colored_logger/logger/colored_logger.py
qt_colored_logger/logger/html_colored_logger.py
qt_colored_logger/src/__init__.py
qt_colored_logger/src/ansi_format.py
qt_colored_logger/src/color_picker.py
qt_colored_logger/text/__init__.py
qt_colored_logger/text/text_buffer.py