Metadata-Version: 2.1
Name: qt-colored-logger
Version: 0.4.0.1
Summary: Powerful functional logger with support for qt programming
Home-page: https://github.com/Nakama3942/qt_colored_logger
Author: Kalynovsky 'Nakama3942' Valentin
Author-email: nakama3942@gmail.com
License: Apache License, Version 2.0, see LICENSE file
Project-URL: Releases, https://github.com/Nakama3942/qt_colored_logger/releases
Classifier: Development Status :: 3 - Alpha
Classifier: Intended Audience :: Developers
Classifier: License :: OSI Approved :: Apache Software License
Classifier: Operating System :: OS Independent
Classifier: Programming Language :: Python :: 3.11
Classifier: Topic :: System :: Logging
Requires-Python: >=3.11
License-File: LICENSE
